<?xml version="1.0" encoding="us-ascii"?><Movement><HandRight><X>0.18279050</X><Y>-0.16986950</Y><Z>0.94089750</Z><Speed>0.00000000</Speed></HandRight><HandRight><X>0.18641950</X><Y>-0.10405910</Y><Z>0.88193370</Z><Speed>2.65307600</Speed></HandRight><HandRight><X>0.19303500</X><Y>-0.18281260</Y><Z>0.95323010</Z><Speed>3.19313800</Speed></HandRight><HandRight><X>-0.11126520</X><Y>-0.14134020</Y><Z>1.06521700</Z><Speed>9.80682400</Speed></HandRight><HandRight><X>0.17871640</X><Y>-0.14556960</Y><Z>0.91157930</Z><Speed>9.84584700</Speed></HandRight><HandRight><X>0.17324770</X><Y>-0.14878060</Y><Z>0.91595640</Z><Speed>0.23116750</Speed></HandRight><HandRight><X>-0.13020450</X><Y>-0.19958090</Y><Z>1.06178500</Z><Speed>10.21454000</Speed></HandRight><HandRight><X>-0.12957180</X><Y>-0.20132330</Y><Z>1.06025900</Z><Speed>0.07202532</Speed></HandRight><HandRight><X>-0.12608050</X><Y>-0.22696360</Y><Z>1.05311300</Z><Speed>0.80536260</Speed></HandRight><HandRight><X>-0.02449792</X><Y>-0.23059800</Y><Z>1.00571900</Z><Speed>3.36460200</Speed></HandRight><HandRight><X>-0.02637145</X><Y>-0.23138690</Y><Z>0.99858770</Z><Speed>0.22246630</Speed></HandRight><HandRight><X>-0.05340505</X><Y>-0.24400700</Y><Z>1.00361600</Z><Speed>0.90765140</Speed></HandRight><HandRight><X>-0.05221019</X><Y>-0.21683360</Y><Z>0.97855380</Z><Speed>1.10957300</Speed></HandRight><HandRight><X>-0.05162513</X><Y>-0.21891090</Y><Z>0.97712760</Z><Speed>0.07760484</Speed></HandRight><HandRight><X>-0.05148742</X><Y>-0.21626600</Y><Z>0.97152910</Z><Speed>0.18580100</Speed></HandRight><HandRight><X>-0.05070510</X><Y>-0.21968410</Y><Z>0.96834110</Z><Speed>0.14217190</Speed></HandRight><HandRight><X>-0.04932172</X><Y>-0.22217220</Y><Z>0.96500890</Z><Speed>0.13148100</Speed></HandRight><HandRight><X>-0.04762493</X><Y>-0.21235900</Y><Z>0.95417230</Z><Speed>0.44152930</Speed></HandRight><HandRight><X>-0.04494517</X><Y>-0.20279070</Y><Z>0.94522580</Z><Speed>0.40111710</Speed></HandRight><HandRight><X>-0.04302040</X><Y>-0.20493230</Y><Z>0.94471910</Z><Speed>0.08771120</Speed></HandRight><HandRight><X>-0.04090554</X><Y>-0.20609500</Y><Z>0.94380680</Z><Speed>0.07740156</Speed></HandRight><HandRight><X>0.11456240</X><Y>-0.24968290</Y><Z>0.91326460</Z><Speed>4.92977800</Speed></HandRight><HandRight><X>0.11835460</X><Y>-0.24953790</Y><Z>0.91336510</Z><Speed>0.11389030</Speed></HandRight><HandRight><X>0.16496310</X><Y>-0.24187000</Y><Z>0.91962590</Z><Speed>1.42944400</Speed></HandRight><HandRight><X>0.16828700</X><Y>-0.24146810</Y><Z>0.91801950</Z><Speed>0.11140620</Speed></HandRight><HandRight><X>0.16496140</X><Y>-0.24348660</Y><Z>0.91473910</Z><Speed>0.15266250</Speed></HandRight><HandRight><X>0.13221770</X><Y>-0.34298480</Y><Z>0.90358280</Z><Speed>3.16019800</Speed></HandRight><HandRight><X>0.13178420</X><Y>-0.34118280</Y><Z>0.90101080</Z><Speed>0.09510438</Speed></HandRight><HandRight><X>0.13141250</X><Y>-0.34072240</Y><Z>0.89870060</Z><Speed>0.07154419</Speed></HandRight><HandRight><X>0.13138620</X><Y>-0.33903580</Y><Z>0.89566670</Z><Speed>0.10413730</Speed></HandRight><HandRight><X>0.13190880</X><Y>-0.34072040</Y><Z>0.89321800</Z><Speed>0.09053548</Speed></HandRight><HandRight><X>0.13339440</X><Y>-0.34228060</Y><Z>0.88920270</Z><Speed>0.13670080</Speed></HandRight><HandRight><X>0.14210690</X><Y>-0.34741730</Y><Z>0.86046150</Z><Speed>0.91406410</Speed></HandRight><HandRight><X>0.14482540</X><Y>-0.34729220</Y><Z>0.85633490</Z><Speed>0.14829410</Speed></HandRight><HandRight><X>0.14456560</X><Y>-0.34835680</Y><Z>0.86415220</Z><Speed>0.23681080</Speed></HandRight><HandRight><X>0.14543970</X><Y>-0.34857550</Y><Z>0.86600200</Z><Speed>0.06172777</Speed></HandRight><HandRight><X>0.24639930</X><Y>-0.33815540</Y><Z>0.81230060</Z><Speed>3.44481300</Speed></HandRight><HandRight><X>0.24713970</X><Y>-0.33729930</Y><Z>0.81307210</Z><Speed>0.04109355</Speed></HandRight><HandRight><X>0.25101650</X><Y>-0.32868330</Y><Z>0.83510680</Z><Speed>0.71924300</Speed></HandRight><HandRight><X>0.32459830</X><Y>-0.34682940</Y><Z>0.80692330</Z><Speed>2.42571300</Speed></HandRight><HandRight><X>0.25022800</X><Y>-0.33415900</Y><Z>0.82091990</Z><Speed>2.30187900</Speed></HandRight><HandRight><X>0.33262140</X><Y>-0.34729290</Y><Z>0.81635770</Z><Speed>2.50674700</Speed></HandRight><HandRight><X>0.33119980</X><Y>-0.34811230</Y><Z>0.81583910</Z><Speed>0.05162461</Speed></HandRight><HandRight><X>0.33138000</X><Y>-0.34934550</Y><Z>0.81573350</Z><Speed>0.03752445</Speed></HandRight><HandRight><X>0.25045080</X><Y>-0.32841660</Y><Z>0.83463590</Z><Speed>2.57106500</Speed></HandRight><HandRight><X>0.25301220</X><Y>-0.31838350</Y><Z>0.84384530</Z><Speed>0.41573190</Speed></HandRight><HandRight><X>0.25359870</X><Y>-0.32007390</Y><Z>0.84072890</Z><Speed>0.10780500</Speed></HandRight><HandRight><X>0.25492380</X><Y>-0.32854580</Y><Z>0.83035490</Z><Speed>0.40377570</Speed></HandRight><HandRight><X>0.25590000</X><Y>-0.33029510</Y><Z>0.82938410</Z><Speed>0.06678075</Speed></HandRight><HandRight><X>0.25362990</X><Y>-0.33116190</Y><Z>0.82718880</Z><Speed>0.09824324</Speed></HandRight><HandRight><X>0.25055140</X><Y>-0.33319120</Y><Z>0.82479160</Z><Speed>0.13193880</Speed></HandRight><HandRight><X>0.25087720</X><Y>-0.33524860</Y><Z>0.82293000</Z><Speed>0.08381017</Speed></HandRight><HandRight><X>0.25184570</X><Y>-0.33662320</Y><Z>0.82175960</Z><Speed>0.06146195</Speed></HandRight><HandRight><X>0.25770990</X><Y>-0.33365070</Y><Z>0.82045440</Z><Speed>0.20108580</Speed></HandRight><HandRight><X>0.25828450</X><Y>-0.33452250</Y><Z>0.82015570</Z><Speed>0.03257971</Speed></HandRight><HandRight><X>0.25648560</X><Y>-0.33688360</Y><Z>0.81713610</Z><Speed>0.12702570</Speed></HandRight><HandRight><X>0.26026230</X><Y>-0.33730610</Y><Z>0.81818310</Z><Speed>0.11825530</Speed></HandRight><HandRight><X>0.25252590</X><Y>-0.33717850</Y><Z>0.81514810</Z><Speed>0.24934420</Speed></HandRight><HandRight><X>0.21416460</X><Y>-0.33211720</Y><Z>0.80736940</Z><Speed>1.18403700</Speed></HandRight><HandRight><X>0.22296120</X><Y>-0.33352570</Y><Z>0.80848870</Z><Speed>0.26936170</Speed></HandRight><HandRight><X>0.25829750</X><Y>-0.33272340</Y><Z>0.81311550</Z><Speed>1.06940900</Speed></HandRight><HandRight><X>0.22075370</X><Y>-0.33434320</Y><Z>0.80861980</Z><Speed>1.13540200</Speed></HandRight><HandRight><X>0.21555440</X><Y>-0.33378190</Y><Z>0.81035240</Z><Speed>0.16527180</Speed></HandRight><HandRight><X>0.21306130</X><Y>-0.33377560</Y><Z>0.81125600</Z><Speed>0.07955213</Speed></HandRight><HandRight><X>0.19781970</X><Y>-0.33641600</Y><Z>0.79050860</Z><Speed>0.77637580</Speed></HandRight><HandRight><X>0.03353935</X><Y>-0.38096750</Y><Z>0.89014440</Z><Speed>5.91693600</Speed></HandRight><HandRight><X>0.06185118</X><Y>-0.37309610</Y><Z>0.86074610</Z><Speed>1.24699700</Speed></HandRight><HandRight><X>0.06107602</X><Y>-0.37408760</Y><Z>0.87599440</Z><Speed>0.45900620</Speed></HandRight><HandRight><X>0.07161574</X><Y>-0.37236540</Y><Z>0.87907730</Z><Speed>0.33346650</Speed></HandRight><HandRight><X>0.06702823</X><Y>-0.37981610</Y><Z>0.86299220</Z><Speed>0.54932480</Speed></HandRight><HandRight><X>0.06759394</X><Y>-0.30135720</Y><Z>0.95412200</Z><Speed>3.60758700</Speed></HandRight><HandRight><X>0.07543086</X><Y>-0.37644450</Y><Z>0.84784410</Z><Speed>3.91089200</Speed></HandRight><HandRight><X>0.07365383</X><Y>-0.37716690</Y><Z>0.84836740</Z><Speed>0.05965119</Speed></HandRight><HandRight><X>0.50617870</X><Y>-0.10292050</Y><Z>0.87574400</Z><Speed>15.38618000</Speed></HandRight><HandRight><X>0.49329500</X><Y>-0.11226500</Y><Z>0.88633530</Z><Speed>0.57353040</Speed></HandRight><HandRight><X>0.55440110</X><Y>-0.28115030</Y><Z>0.92960330</Z><Speed>5.54215900</Speed></HandRight><HandRight><X>0.50760760</X><Y>-0.21117410</Y><Z>0.95681740</Z><Speed>2.65409400</Speed></HandRight><HandRight><X>0.50762060</X><Y>-0.21114780</Y><Z>0.95688120</Z><Speed>0.00210422</Speed></HandRight><HandRight><X>0.50587150</X><Y>-0.21928170</Y><Z>0.95383490</Z><Speed>0.26579940</Speed></HandRight><HandRight><X>0.50562130</X><Y>-0.22100200</Y><Z>0.95270190</Z><Speed>0.06224947</Speed></HandRight><HandRight><X>0.50816380</X><Y>-0.21034390</Y><Z>0.95536900</Z><Speed>0.33831250</Speed></HandRight><HandRight><X>0.49396570</X><Y>-0.34030220</Y><Z>0.95311600</Z><Speed>3.92253000</Speed></HandRight><HandRight><X>0.73295870</X><Y>-0.09903051</Y><Z>0.93852180</Z><Speed>10.19747000</Speed></HandRight><HandRight><X>0.73452130</X><Y>-0.08754129</Y><Z>0.95183330</Z><Speed>0.52960000</Speed></HandRight><HandRight><X>0.73405610</X><Y>-0.08240162</Y><Z>0.96754260</Z><Speed>0.49605720</Speed></HandRight><HandRight><X>0.73226560</X><Y>-0.07684719</Y><Z>0.98261200</Z><Speed>0.48479800</Speed></HandRight><HandRight><X>0.72998140</X><Y>-0.07466681</Y><Z>0.99417220</Z><Speed>0.35951180</Speed></HandRight><HandRight><X>0.72668410</X><Y>-0.07145537</Y><Z>1.00317000</Z><Speed>0.30319090</Speed></HandRight><HandRight><X>0.72206620</X><Y>-0.07028639</Y><Z>1.00920200</Z><Speed>0.23058970</Speed></HandRight><HandRight><X>0.71834190</X><Y>-0.06949259</Y><Z>1.01328900</Z><Speed>0.16759650</Speed></HandRight><HandRight><X>0.43924330</X><Y>-0.25978350</Y><Z>1.18710800</Z><Speed>11.39682000</Speed></HandRight><HandRight><X>0.51931520</X><Y>-0.28104600</Y><Z>1.15819300</Z><Speed>2.63243500</Speed></HandRight><HandRight><X>0.34839840</X><Y>-0.23020570</Y><Z>1.17678300</Z><Speed>5.37853300</Speed></HandRight><HandRight><X>0.32323830</X><Y>-0.21363110</Y><Z>1.17167000</Z><Speed>0.91678940</Speed></HandRight><HandRight><X>0.32265940</X><Y>-0.21083470</Y><Z>1.17486300</Z><Speed>0.12849300</Speed></HandRight><HandRight><X>0.31425970</X><Y>-0.19210140</Y><Z>1.18082700</Z><Speed>0.64137010</Speed></HandRight><HandRight><X>0.44376080</X><Y>0.05960737</Y><Z>0.81118880</Z><Speed>13.96725000</Speed></HandRight><HandRight><X>0.45465210</X><Y>0.06551214</Y><Z>0.84066670</Z><Speed>0.95926590</Speed></HandRight><HandRight><X>0.34067670</X><Y>0.14841260</Y><Z>0.77834310</Z><Speed>4.62302900</Speed></HandRight><HandRight><X>0.46086080</X><Y>0.04570943</Y><Z>0.81838590</Z><Speed>4.89244700</Speed></HandRight><HandRight><X>0.46467750</X><Y>0.03591861</Y><Z>0.82193270</Z><Speed>0.33272580</Speed></HandRight><HandRight><X>0.45745460</X><Y>0.02748741</Y><Z>0.78476930</Z><Speed>1.16358900</Speed></HandRight><HandRight><X>0.37579110</X><Y>0.03019972</Y><Z>0.84959290</Z><Speed>3.12898500</Speed></HandRight><HandRight><X>0.37277910</X><Y>0.03151441</Y><Z>0.84968470</Z><Speed>0.09863117</Speed></HandRight><HandRight><X>0.36424300</X><Y>0.03743470</Y><Z>0.84968400</Z><Speed>0.31164700</Speed></HandRight><HandRight><X>0.45922840</X><Y>0.19182140</Y><Z>0.74561980</Z><Speed>6.27041800</Speed></HandRight><HandRight><X>0.18820960</X><Y>0.20074280</Y><Z>0.78986810</Z><Speed>8.24255900</Speed></HandRight><HandRight><X>0.18603440</X><Y>0.21097010</Y><Z>0.78136620</Z><Speed>0.40428700</Speed></HandRight><HandRight><X>0.31019090</X><Y>0.15405870</Y><Z>0.71208720</Z><Speed>4.59434300</Speed></HandRight><HandRight><X>0.29509370</X><Y>0.21961030</Y><Z>0.72417200</Z><Speed>2.05033900</Speed></HandRight><HandRight><X>0.28976600</X><Y>0.22163680</Y><Z>0.73008070</Z><Speed>0.24629870</Speed></HandRight><HandRight><X>0.29008230</X><Y>0.23097810</Y><Z>0.72715270</Z><Speed>0.29383700</Speed></HandRight><HandRight><X>0.27967700</X><Y>0.23564980</Y><Z>0.73424900</Z><Speed>0.40299920</Speed></HandRight><HandRight><X>0.25641870</X><Y>0.24432180</Y><Z>0.73182840</Z><Speed>0.74820440</Speed></HandRight><HandRight><X>0.25615220</X><Y>0.24584200</Y><Z>0.73451820</Z><Speed>0.09303410</Speed></HandRight><HandRight><X>0.26474240</X><Y>0.24245080</Y><Z>0.73494710</Z><Speed>0.27736210</Speed></HandRight><HandRight><X>0.28190780</X><Y>0.12893020</Y><Z>0.83497950</Z><Speed>4.56828600</Speed></HandRight><HandRight><X>0.17920300</X><Y>0.20084600</Y><Z>0.80392930</Z><Speed>3.87502700</Speed></HandRight><HandRight><X>0.25440810</X><Y>0.14002830</Y><Z>0.73866200</Z><Speed>3.50042600</Speed></HandRight><HandRight><X>0.30055620</X><Y>0.14491580</Y><Z>0.77347000</Z><Speed>1.74029300</Speed></HandRight><HandRight><X>0.37547950</X><Y>0.08859113</Y><Z>0.76963430</Z><Speed>2.81435800</Speed></HandRight><HandRight><X>0.54860450</X><Y>-0.09144848</Y><Z>0.71537820</Z><Speed>7.66793500</Speed></HandRight><HandRight><X>0.55254240</X><Y>-0.10676630</Y><Z>0.71985720</Z><Speed>0.49313720</Speed></HandRight><HandRight><X>0.54332610</X><Y>-0.09160078</Y><Z>0.71264600</Z><Speed>0.57466590</Speed></HandRight><HandRight><X>0.42442040</X><Y>0.00671844</Y><Z>0.68272470</Z><Speed>4.71492100</Speed></HandRight><HandRight><X>0.41686260</X><Y>0.00784903</Y><Z>0.69058770</Z><Speed>0.32894060</Speed></HandRight><HandRight><X>0.34524230</X><Y>0.04318971</Y><Z>0.73740050</Z><Speed>2.77720900</Speed></HandRight><HandRight><X>0.42726450</X><Y>-0.01149639</Y><Z>0.74886180</Z><Speed>2.97735200</Speed></HandRight><HandRight><X>0.37369730</X><Y>-0.04655171</Y><Z>0.83960810</Z><Speed>3.33165000</Speed></HandRight><HandRight><X>0.35728030</X><Y>-0.02927375</Y><Z>0.83588170</Z><Speed>0.72369820</Speed></HandRight><HandRight><X>0.36192290</X><Y>-0.03404930</Y><Z>0.83995400</Z><Speed>0.23419930</Speed></HandRight><HandRight><X>0.42476110</X><Y>0.06964836</Y><Z>0.73073230</Z><Speed>4.89572200</Speed></HandRight><HandRight><X>0.28293370</X><Y>0.06884092</Y><Z>0.73038430</Z><Speed>4.25490400</Speed></HandRight><HandRight><X>0.25772720</X><Y>0.04490999</Y><Z>0.72765990</Z><Speed>1.04591100</Speed></HandRight><HandRight><X>0.24229420</X><Y>0.05843404</Y><Z>0.72384490</Z><Speed>0.62615260</Speed></HandRight><HandRight><X>0.23874110</X><Y>0.06210839</Y><Z>0.73215470</Z><Speed>0.29267830</Speed></HandRight><HandRight><X>0.17782180</X><Y>0.09063897</Y><Z>0.79997900</Z><Speed>2.86579200</Speed></HandRight><HandRight><X>0.17087640</X><Y>0.09222337</Y><Z>0.79752080</Z><Speed>0.22608030</Speed></HandRight><HandRight><X>0.16096760</X><Y>0.09465207</Y><Z>0.79322340</Z><Speed>0.33210640</Speed></HandRight><HandRight><X>0.29090410</X><Y>0.20547120</Y><Z>0.78387250</Z><Speed>5.13094800</Speed></HandRight><HandRight><X>0.29298180</X><Y>0.20952430</Y><Z>0.78308650</Z><Speed>0.13865920</Speed></HandRight><HandRight><X>0.29419650</X><Y>0.21034120</Y><Z>0.78241630</Z><Speed>0.04830011</Speed></HandRight><HandRight><X>0.30083310</X><Y>0.21034190</Y><Z>0.77719950</Z><Speed>0.25324460</Speed></HandRight><HandRight><X>0.30574140</X><Y>0.20929620</Y><Z>0.77618410</Z><Speed>0.15360630</Speed></HandRight><HandRight><X>0.31080170</X><Y>0.20770260</Y><Z>0.77638490</Z><Speed>0.15927110</Speed></HandRight><HandRight><X>0.30786940</X><Y>0.20264060</Y><Z>0.77642510</Z><Speed>0.17550270</Speed></HandRight><HandRight><X>0.14709570</X><Y>0.09922484</Y><Z>0.78773280</Z><Speed>5.74489500</Speed></HandRight><HandRight><X>0.36760040</X><Y>0.17389480</Y><Z>0.75227670</Z><Speed>7.06467200</Speed></HandRight><HandRight><X>0.11760720</X><Y>-0.02123677</Y><Z>0.79358220</Z><Speed>9.59433300</Speed></HandRight><HandRight><X>0.12439120</X><Y>-0.01036687</Y><Z>0.78820150</Z><Speed>0.41691400</Speed></HandRight><HandRight><X>0.16126770</X><Y>-0.15947360</Y><Z>0.77394740</Z><Speed>4.62777400</Speed></HandRight><HandRight><X>0.13534400</X><Y>-0.07110129</Y><Z>0.76815140</Z><Speed>2.76835200</Speed></HandRight><HandRight><X>0.19722490</X><Y>-0.20294580</Y><Z>0.75592130</Z><Speed>4.38470400</Speed></HandRight><HandRight><X>0.33517450</X><Y>-0.28494250</Y><Z>0.78560000</Z><Speed>4.89601400</Speed></HandRight><HandRight><X>0.42872940</X><Y>-0.26147560</Y><Z>0.78040940</Z><Speed>2.89778100</Speed></HandRight><HandRight><X>0.48774350</X><Y>-0.23562260</Y><Z>0.79675770</Z><Speed>1.99411100</Speed></HandRight><HandRight><X>0.36362270</X><Y>-0.12975060</Y><Z>0.84789300</Z><Speed>5.12900800</Speed></HandRight><HandRight><X>0.36393230</X><Y>-0.14076830</Y><Z>0.84821780</Z><Speed>0.33080480</Speed></HandRight><HandRight><X>0.36606230</X><Y>-0.15560720</Y><Z>0.84973540</Z><Speed>0.45203040</Speed></HandRight><HandRight><X>0.36608970</X><Y>-0.16359930</Y><Z>0.85221330</Z><Speed>0.25102200</Speed></HandRight><HandRight><X>0.35932010</X><Y>-0.17126010</Y><Z>0.85060230</Z><Speed>0.31048330</Speed></HandRight><HandRight><X>0.35602430</X><Y>-0.17720060</Y><Z>0.85125200</Z><Speed>0.20473530</Speed></HandRight><HandRight><X>0.35607090</X><Y>-0.19348240</Y><Z>0.85108630</Z><Speed>0.48848040</Speed></HandRight><HandRight><X>0.35395470</X><Y>-0.19436350</Y><Z>0.85198920</Z><Speed>0.07390933</Speed></HandRight><HandRight><X>0.34747380</X><Y>-0.19624710</Y><Z>0.85113110</Z><Speed>0.20410230</Speed></HandRight><HandRight><X>0.34523710</X><Y>-0.19842470</Y><Z>0.85162460</Z><Speed>0.09481285</Speed></HandRight><HandRight><X>0.34295830</X><Y>-0.20034610</Y><Z>0.85093840</Z><Speed>0.09175964</Speed></HandRight><HandRight><X>0.34160030</X><Y>-0.20107640</Y><Z>0.85078250</Z><Speed>0.04649409</Speed></HandRight><HandRight><X>0.34144800</X><Y>-0.20177460</Y><Z>0.85081740</Z><Speed>0.02146591</Speed></HandRight><HandRight><X>0.34147840</X><Y>-0.20174530</Y><Z>0.85073910</Z><Speed>0.00267072</Speed></HandRight><HandRight><X>0.34210720</X><Y>-0.20047850</Y><Z>0.85015460</Z><Speed>0.04590781</Speed></HandRight><HandRight><X>0.34914750</X><Y>-0.19915300</Y><Z>0.85242470</Z><Speed>0.22545090</Speed></HandRight><HandRight><X>0.35507980</X><Y>-0.19688670</Y><Z>0.85325330</Z><Speed>0.19212790</Speed></HandRight><HandRight><X>0.36189340</X><Y>-0.19277620</Y><Z>0.85448930</Z><Speed>0.24158670</Speed></HandRight><HandRight><X>0.36529290</X><Y>-0.19202470</Y><Z>0.85440040</Z><Speed>0.10448110</Speed></HandRight><HandRight><X>0.36939280</X><Y>-0.18939060</Y><Z>0.85418890</Z><Speed>0.14633290</Speed></HandRight><HandRight><X>0.36983480</X><Y>-0.18908190</Y><Z>0.85371540</Z><Speed>0.02152638</Speed></HandRight><HandRight><X>0.37064190</X><Y>-0.18766730</Y><Z>0.85302000</Z><Speed>0.05312745</Speed></HandRight><HandRight><X>0.37149820</X><Y>-0.18535300</Y><Z>0.85238800</Z><Speed>0.07641800</Speed></HandRight><HandRight><X>0.37166610</X><Y>-0.18426920</Y><Z>0.85247340</Z><Speed>0.03300020</Speed></HandRight><HandRight><X>0.37174510</X><Y>-0.18266790</Y><Z>0.85245290</Z><Speed>0.04810118</Speed></HandRight><HandRight><X>0.37261410</X><Y>-0.17819770</Y><Z>0.85211430</Z><Speed>0.13699590</Speed></HandRight><HandRight><X>0.37313760</X><Y>-0.17521490</Y><Z>0.85216090</Z><Speed>0.09086074</Speed></HandRight><HandRight><X>0.37303210</X><Y>-0.17247310</Y><Z>0.85202310</Z><Speed>0.08241992</Speed></HandRight><HandRight><X>0.37240240</X><Y>-0.17052490</Y><Z>0.85187690</Z><Speed>0.06157931</Speed></HandRight><HandRight><X>0.37211780</X><Y>-0.16906120</Y><Z>0.85166480</Z><Speed>0.04518261</Speed></HandRight><HandRight><X>0.37049400</X><Y>-0.16762370</Y><Z>0.85143520</Z><Speed>0.06542300</Speed></HandRight><HandRight><X>0.36816020</X><Y>-0.16596150</Y><Z>0.85083880</Z><Speed>0.08780059</Speed></HandRight><HandRight><X>0.36668310</X><Y>-0.16486500</Y><Z>0.85013990</Z><Speed>0.05903595</Speed></HandRight><HandRight><X>0.36520730</X><Y>-0.16296090</Y><Z>0.84870590</Z><Speed>0.08410475</Speed></HandRight><HandRight><X>0.36423180</X><Y>-0.16150050</Y><Z>0.84831530</Z><Speed>0.05397506</Speed></HandRight><HandRight><X>0.36368050</X><Y>-0.15580510</Y><Z>0.84664910</Z><Speed>0.17879280</Speed></HandRight><HandRight><X>0.36308930</X><Y>-0.14975820</Y><Z>0.84546310</Z><Speed>0.18571180</Speed></HandRight><HandRight><X>0.36238860</X><Y>-0.13961280</Y><Z>0.84367210</Z><Speed>0.30978210</Speed></HandRight><HandRight><X>0.36151370</X><Y>-0.12682690</Y><Z>0.84250710</Z><Speed>0.38605960</Speed></HandRight><HandRight><X>0.35881030</X><Y>-0.12814890</Y><Z>0.84355780</Z><Speed>0.09562464</Speed></HandRight><HandRight><X>0.35402210</X><Y>-0.09930314</Y><Z>0.83849810</Z><Speed>0.89025080</Speed></HandRight><HandRight><X>0.45046930</X><Y>0.08219413</Y><Z>0.68801130</Z><Speed>7.64203100</Speed></HandRight><HandRight><X>0.30956420</X><Y>-0.05319980</Y><Z>0.83129310</Z><Speed>7.26938000</Speed></HandRight><HandRight><X>0.09581529</X><Y>0.05028549</Y><Z>0.80782560</Z><Speed>7.15916700</Speed></HandRight><HandRight><X>0.02485839</X><Y>-0.01571088</Y><Z>0.82730360</Z><Speed>2.96526800</Speed></HandRight><HandRight><X>0.01846772</X><Y>-0.03029175</Y><Z>0.82329150</Z><Speed>0.49252970</Speed></HandRight><HandRight><X>0.01416197</X><Y>-0.01043090</Y><Z>0.85179280</Z><Speed>1.05013500</Speed></HandRight><HandRight><X>-0.06604507</X><Y>0.01896970</Y><Z>0.84690200</Z><Speed>2.56697000</Speed></HandRight><HandRight><X>-0.05886077</X><Y>0.02426651</Y><Z>0.84743120</Z><Speed>0.26824500</Speed></HandRight><HandRight><X>-0.05766771</X><Y>0.07044890</Y><Z>0.83430520</Z><Speed>1.44079000</Speed></HandRight><HandRight><X>0.31801660</X><Y>0.02487713</Y><Z>0.71642240</Z><Speed>11.89120000</Speed></HandRight><HandRight><X>0.12183020</X><Y>-0.02377407</Y><Z>0.75584590</Z><Speed>6.17812500</Speed></HandRight><HandRight><X>0.12790370</X><Y>-0.04385816</Y><Z>0.73852370</Z><Speed>0.81626360</Speed></HandRight><HandRight><X>0.14460300</X><Y>-0.03738903</Y><Z>0.74200060</Z><Speed>0.54728840</Speed></HandRight><HandRight><X>0.14546210</X><Y>-0.03676030</Y><Z>0.74437270</Z><Speed>0.07800080</Speed></HandRight><HandRight><X>0.05846806</X><Y>-0.04626231</Y><Z>0.79179330</Z><Speed>2.98601300</Speed></HandRight><HandRight><X>0.16093380</X><Y>-0.02291834</Y><Z>0.73560190</Z><Speed>3.57512100</Speed></HandRight><HandRight><X>0.30953310</X><Y>-0.05053584</Y><Z>0.83510350</Z><Speed>5.42867600</Speed></HandRight><HandRight><X>0.11792150</X><Y>0.06927937</Y><Z>0.79504610</Z><Speed>6.88532700</Speed></HandRight><HandRight><X>0.11153040</X><Y>0.07185290</Y><Z>0.80202380</Z><Speed>0.29418020</Speed></HandRight><HandRight><X>0.08321647</X><Y>0.03921178</Y><Z>0.79841490</Z><Speed>1.30081900</Speed></HandRight><HandRight><X>-0.06244450</X><Y>0.04876858</Y><Z>0.83324940</Z><Speed>4.50218900</Speed></HandRight><HandRight><X>0.20530610</X><Y>-0.01354904</Y><Z>0.83245660</Z><Speed>8.24724500</Speed></HandRight><HandRight><X>0.24722240</X><Y>-0.05790570</Y><Z>0.82577090</Z><Speed>1.84181100</Speed></HandRight><HandRight><X>0.25001620</X><Y>-0.05809282</Y><Z>0.82560310</Z><Speed>0.08415224</Speed></HandRight></Movement>